pythonista_stubs/_cb.pyi
pythonista_stubs/py.typed
pythonista_stubs/pythonista_stubs/__init__.pyi
pythonista_stubs/pythonista_stubs/appex.pyi
pythonista_stubs/pythonista_stubs/canvas.pyi
pythonista_stubs/pythonista_stubs/cb.pyi
pythonista_stubs/pythonista_stubs/clipboard.pyi
pythonista_stubs/pythonista_stubs/console.pyi
pythonista_stubs/pythonista_stubs/contacts.pyi
pythonista_stubs/pythonista_stubs/dialogs.pyi
pythonista_stubs/pythonista_stubs/editor.pyi
pythonista_stubs/pythonista_stubs/keyboard.pyi
pythonista_stubs/pythonista_stubs/keychain.pyi
pythonista_stubs/pythonista_stubs/linguistictagger.pyi
pythonista_stubs/pythonista_stubs/location.pyi
pythonista_stubs/pythonista_stubs/motion.pyi
pythonista_stubs/pythonista_stubs/notification.pyi
pythonista_stubs/pythonista_stubs/objc_util.pyi
pythonista_stubs/pythonista_stubs/photos.pyi
pythonista_stubs/pythonista_stubs/py.typed
pythonista_stubs/pythonista_stubs/reminders.pyi
pythonista_stubs/pythonista_stubs/shortcuts.pyi
pythonista_stubs/pythonista_stubs/sound.pyi
pythonista_stubs/pythonista_stubs/speech.pyi
pythonista_stubs/pythonista_stubs/ui.pyi
pythonista_stubs/pythonista_stubs.egg-info/PKG-INFO
pythonista_stubs/pythonista_stubs.egg-info/SOURCES.txt
pythonista_stubs/pythonista_stubs.egg-info/dependency_links.txt
pythonista_stubs/pythonista_stubs.egg-info/requires.txt
pythonista_stubs/pythonista_stubs.egg-info/top_level.txt
pythonista_stubs-3.4.1.dist-info/licenses/LICENSE
pythonista_stubs-3.4.1.dist-info/METADATA
pythonista_stubs-3.4.1.dist-info/WHEEL
pythonista_stubs-3.4.1.dist-info/top_level.txt
pythonista_stubs-3.4.1.dist-info/RECORD
