Metadata-Version: 2.4
Name: pythonista-stubs
Version: 3.4.1
Summary: A collection of Pythonista stub files
Author: Dmytro Yaroshenko
Author-email: Harold Martin <Harold.Martin@gmail.com>
License:                                  Apache License
Project-URL: Homepage, https://github.com/hbmartin/pythonista-stubs
Project-URL: Bug Reports, https://github.com/hbmartin/pythonista-stubs/issues
Project-URL: Source, https://github.com/hbmartin/pythonista-stubs
Keywords: pythonista,stubs,ios,ide
Classifier: Intended Audience :: Developers
Classifier: Natural Language :: English
Classifier: Programming Language :: Python
Classifier: Topic :: Software Development :: Libraries :: Python Modules
Classifier: Programming Language :: Python :: 3
Classifier: Programming Language :: Python :: 3 :: Only
Classifier: Programming Language :: Python :: 3.10
Classifier: Programming Language :: Python :: 3.11
Classifier: Programming Language :: Python :: 3.12
Classifier: Programming Language :: Python :: 3.13
Classifier: Programming Language :: Python :: Implementation :: CPython
Requires-Python: >=3.10
License-File: LICENSE
Requires-Dist: types-pillow>=10.2.0.20240822
Requires-Dist: typing-extensions>=4.14.1
Dynamic: license-file
